channel_integrations/__init__.py
channel_integrations/catalog_service_utils.py
channel_integrations/exceptions.py
channel_integrations/lms_utils.py
channel_integrations/urls.py
channel_integrations/utils.py
channel_integrations/api/__init__.py
channel_integrations/api/serializers.py
channel_integrations/api/urls.py
channel_integrations/api/v1/__init__.py
channel_integrations/api/v1/mixins.py
channel_integrations/api/v1/urls.py
channel_integrations/api/v1/views.py
channel_integrations/api/v1/blackboard/__init__.py
channel_integrations/api/v1/blackboard/serializers.py
channel_integrations/api/v1/blackboard/urls.py
channel_integrations/api/v1/blackboard/views.py
channel_integrations/api/v1/canvas/__init__.py
channel_integrations/api/v1/canvas/serializers.py
channel_integrations/api/v1/canvas/urls.py
channel_integrations/api/v1/canvas/views.py
channel_integrations/api/v1/cornerstone/__init__.py
channel_integrations/api/v1/cornerstone/serializers.py
channel_integrations/api/v1/cornerstone/urls.py
channel_integrations/api/v1/cornerstone/views.py
channel_integrations/api/v1/degreed2/__init__.py
channel_integrations/api/v1/degreed2/serializers.py
channel_integrations/api/v1/degreed2/urls.py
channel_integrations/api/v1/degreed2/views.py
channel_integrations/api/v1/logs/__init__.py
channel_integrations/api/v1/logs/serializers.py
channel_integrations/api/v1/logs/urls.py
channel_integrations/api/v1/logs/views.py
channel_integrations/api/v1/moodle/__init__.py
channel_integrations/api/v1/moodle/serializers.py
channel_integrations/api/v1/moodle/urls.py
channel_integrations/api/v1/moodle/views.py
channel_integrations/api/v1/sap_success_factors/__init__.py
channel_integrations/api/v1/sap_success_factors/serializers.py
channel_integrations/api/v1/sap_success_factors/urls.py
channel_integrations/api/v1/sap_success_factors/views.py
channel_integrations/blackboard/__init__.py
channel_integrations/blackboard/apps.py
channel_integrations/blackboard/client.py
enterprise_integrated_channels-0.1.36.dist-info/licenses/LICENSE
enterprise_integrated_channels-0.1.36.dist-info/licenses/LICENSE.txt
enterprise_integrated_channels-0.1.36.dist-info/METADATA
enterprise_integrated_channels-0.1.36.dist-info/WHEEL
enterprise_integrated_channels-0.1.36.dist-info/top_level.txt
enterprise_integrated_channels-0.1.36.dist-info/RECORD
