Metadata-Version: 2.4
Name: enterprise-integrated-channels
Version: 0.1.36
Summary: An integrated channel is an abstraction meant to represent a third-party system                 which provides an API that can be used to transmit EdX data to the third-party system.
Home-page: https://github.com/openedx/enterprise-integrated-channels
Author: Open edX Project
Author-email: oscm@openedx.org
License: AGPL 3.0
Keywords: Python edx
Classifier: Development Status :: 3 - Alpha
Classifier: Framework :: Django
Classifier: Framework :: Django :: 4.2
Classifier: Framework :: Django :: 5.2
Classifier: Intended Audience :: Developers
Classifier: License :: OSI Approved :: GNU Affero General Public License v3 or later (AGPLv3+)
Classifier: Natural Language :: English
Classifier: Programming Language :: Python :: 3
Classifier: Programming Language :: Python :: 3.11
Requires-Python: >=3.11
License-File: LICENSE
License-File: LICENSE.txt
Requires-Dist: Django>=4.2
Requires-Dist: celery
Requires-Dist: django-config-models
Requires-Dist: django-fernet-fields-v2
Requires-Dist: django-model-utils
Requires-Dist: django-oauth-toolkit
Requires-Dist: django-object-actions
Requires-Dist: django-simple-history
Requires-Dist: edx-drf-extensions
Requires-Dist: edx-opaque-keys[django]
Requires-Dist: edx-rbac
Requires-Dist: edx-rest-api-client
Requires-Dist: edx-tincan-py35
Requires-Dist: edx_django_utils
Requires-Dist: jsonfield
Requires-Dist: openedx-atlas
Requires-Dist: pytz
Requires-Dist: requests
Requires-Dist: slumber
Requires-Dist: snowflake-connector-python<4.0.0,>=3.18.0
Requires-Dist: unicodecsv
Dynamic: author
Dynamic: author-email
Dynamic: classifier
Dynamic: description
Dynamic: description-content-type
Dynamic: home-page
Dynamic: keywords
Dynamic: license
Dynamic: license-file
Dynamic: requires-dist
Dynamic: requires-python
Dynamic: summary
